{
  "updatedAt": "2026-06-04T16:37:17.573Z",
  "google": [],
  "domestic": [
    {
      "rank": 1,
      "keyword": "투표용지 부족 헌법소원 접수",
      "state": "s",
      "change": "0"
    },
    {
      "rank": 2,
      "keyword": "김혜경 여사, 한불수교 140주년 참석",
      "state": "+",
      "change": "1"
    },
    {
      "rank": 3,
      "keyword": "젠슨 황, 내일 방한 일정 공개",
      "state": "-",
      "change": "1"
    },
    {
      "rank": 4,
      "keyword": "여자배구 SOOP 감독 김세진",
      "state": "+",
      "change": "2"
    },
    {
      "rank": 5,
      "keyword": "유준원 새 소속사 무시",
      "state": "n",
      "change": "0"
    },
    {
      "rank": 6,
      "keyword": "우천 중단 경기",
      "state": "+",
      "change": "1"
    },
    {
      "rank": 7,
      "keyword": "도수치료 주 2회 제한",
      "state": "n",
      "change": "0"
    },
    {
      "rank": 8,
      "keyword": "환율 1540원 금융위기",
      "state": "+",
      "change": "1"
    },
    {
      "rank": 9,
      "keyword": "조국, 당대표직 사퇴",
      "state": "n",
      "change": "0"
    },
    {
      "rank": 10,
      "keyword": "어도어 손해배상 330억",
      "state": "+",
      "change": "15"
    }
  ]
}