{
  "updatedAt": "2026-06-14T16:49:17.398Z",
  "google": [
    {
      "rank": 1,
      "keyword": "이준영",
      "traffic": "200+"
    },
    {
      "rank": 2,
      "keyword": "태연",
      "traffic": "200+"
    },
    {
      "rank": 3,
      "keyword": "페라리",
      "traffic": "200+"
    },
    {
      "rank": 4,
      "keyword": "주유소",
      "traffic": "200+"
    },
    {
      "rank": 5,
      "keyword": "루이스 해밀턴",
      "traffic": "200+"
    },
    {
      "rank": 6,
      "keyword": "박인희",
      "traffic": "200+"
    },
    {
      "rank": 7,
      "keyword": "현대로템",
      "traffic": "200+"
    },
    {
      "rank": 8,
      "keyword": "미군",
      "traffic": "500+"
    },
    {
      "rank": 9,
      "keyword": "손태영",
      "traffic": "100+"
    },
    {
      "rank": 10,
      "keyword": "jtbc 실시간",
      "traffic": "100+"
    }
  ],
  "domestic": [
    {
      "rank": 1,
      "keyword": "이재명 대통령 특별미사",
      "state": "s",
      "change": "0"
    },
    {
      "rank": 2,
      "keyword": "김민솔 한국여자오픈 우승",
      "state": "s",
      "change": "0"
    },
    {
      "rank": 3,
      "keyword": "샤이니 키, 6개월 만에 SNS 재개",
      "state": "n",
      "change": "0"
    },
    {
      "rank": 4,
      "keyword": "주연·단역 열애설",
      "state": "s",
      "change": "0"
    },
    {
      "rank": 5,
      "keyword": "이스라엘 베이루트 공습",
      "state": "+",
      "change": "1"
    },
    {
      "rank": 6,
      "keyword": "사랑을 처방해 드립니다",
      "state": "-",
      "change": "1"
    },
    {
      "rank": 7,
      "keyword": "李대통령 음모론 반사회적 행태",
      "state": "+",
      "change": "1"
    },
    {
      "rank": 8,
      "keyword": "강예원 부친 빚 눈물",
      "state": "-",
      "change": "4"
    },
    {
      "rank": 9,
      "keyword": "여자배구 대만 꺾고 우승",
      "state": "+",
      "change": "16"
    },
    {
      "rank": 10,
      "keyword": "신입사원 강회장",
      "state": "-",
      "change": "3"
    }
  ]
}