{
  "updatedAt": "2026-06-19T23:44:48.560Z",
  "google": [
    {
      "rank": 1,
      "keyword": "마카오 오픈",
      "traffic": "200+"
    },
    {
      "rank": 2,
      "keyword": "모로코",
      "traffic": "200+"
    },
    {
      "rank": 3,
      "keyword": "성빈",
      "traffic": "500+"
    },
    {
      "rank": 4,
      "keyword": "天氣",
      "traffic": "100+"
    },
    {
      "rank": 5,
      "keyword": "jadwal piala dunia 2026",
      "traffic": "100+"
    },
    {
      "rank": 6,
      "keyword": "날씨",
      "traffic": "200000+"
    },
    {
      "rank": 7,
      "keyword": "스포티비뉴스",
      "traffic": "200+"
    },
    {
      "rank": 8,
      "keyword": "weather",
      "traffic": "2000+"
    },
    {
      "rank": 9,
      "keyword": "농협은행",
      "traffic": "100+"
    },
    {
      "rank": 10,
      "keyword": "아이폰",
      "traffic": "100+"
    }
  ],
  "domestic": [
    {
      "rank": 1,
      "keyword": "월드컵 일정",
      "state": "s",
      "change": "0"
    },
    {
      "rank": 2,
      "keyword": "멋진 신세계, 최고 시청률 경신",
      "state": "+",
      "change": "2"
    },
    {
      "rank": 3,
      "keyword": "트럼프 60일 내 합의 요구",
      "state": "n",
      "change": "0"
    },
    {
      "rank": 4,
      "keyword": "이화영 술 파티 위증 징역 4개월",
      "state": "+",
      "change": "1"
    },
    {
      "rank": 5,
      "keyword": "신입사원 강회장",
      "state": "+",
      "change": "1"
    },
    {
      "rank": 6,
      "keyword": "김신영 주사 논란",
      "state": "n",
      "change": "0"
    },
    {
      "rank": 7,
      "keyword": "이기혁 SNS 악플 세례",
      "state": "n",
      "change": "0"
    },
    {
      "rank": 8,
      "keyword": "신민아 10년 결혼관",
      "state": "n",
      "change": "0"
    },
    {
      "rank": 9,
      "keyword": "멕시코 유망주 이강인 좋은 선수",
      "state": "n",
      "change": "0"
    },
    {
      "rank": 10,
      "keyword": "경찰 잘못 버린 사람 다리",
      "state": "n",
      "change": "0"
    }
  ]
}