{
  "updatedAt": "2026-05-08T21:43:26.458Z",
  "google": [
    {
      "rank": 1,
      "keyword": "3기신도시 남양주 왕숙지구",
      "traffic": "200+"
    },
    {
      "rank": 2,
      "keyword": "지역화폐",
      "traffic": "100+"
    },
    {
      "rank": 3,
      "keyword": "중국",
      "traffic": "1000+"
    },
    {
      "rank": 4,
      "keyword": "광 통신",
      "traffic": "100+"
    },
    {
      "rank": 5,
      "keyword": "김진하",
      "traffic": "100+"
    },
    {
      "rank": 6,
      "keyword": "김경문",
      "traffic": "1000+"
    },
    {
      "rank": 7,
      "keyword": "마크 도스 산토스",
      "traffic": "200+"
    },
    {
      "rank": 8,
      "keyword": "도박",
      "traffic": "100+"
    },
    {
      "rank": 9,
      "keyword": "관세",
      "traffic": "5000+"
    },
    {
      "rank": 10,
      "keyword": "김다현",
      "traffic": "200+"
    }
  ],
  "domestic": [
    {
      "rank": 1,
      "keyword": "백상예술대상 수상자들",
      "state": "+",
      "change": "1"
    },
    {
      "rank": 2,
      "keyword": "김영재의 대군부인 출연",
      "state": "-",
      "change": "1"
    },
    {
      "rank": 3,
      "keyword": "이란 유조선 2척 무력화",
      "state": "s",
      "change": "0"
    },
    {
      "rank": 4,
      "keyword": "U-17 여자축구 북한에 0-3 패",
      "state": "n",
      "change": "0"
    },
    {
      "rank": 5,
      "keyword": "신현빈, 레드카펫 해프닝 웃음",
      "state": "+",
      "change": "4"
    },
    {
      "rank": 6,
      "keyword": "첫 번째 남자",
      "state": "s",
      "change": "0"
    },
    {
      "rank": 7,
      "keyword": "나 혼자 산다",
      "state": "-",
      "change": "2"
    },
    {
      "rank": 8,
      "keyword": "연장 11회 LG 승리",
      "state": "-",
      "change": "1"
    },
    {
      "rank": 9,
      "keyword": "트럼프, 러-우 3일 휴전 포로 교환",
      "state": "+",
      "change": "7"
    },
    {
      "rank": 10,
      "keyword": "신혜선, 트임 드레스 흠잡을 데 없어",
      "state": "+",
      "change": "1"
    }
  ]
}