{
  "updatedAt": "2026-05-23T05:02:55.493Z",
  "google": [
    {
      "rank": 1,
      "keyword": "폴 피어스",
      "traffic": "100+"
    },
    {
      "rank": 2,
      "keyword": "제이쓴",
      "traffic": "100+"
    },
    {
      "rank": 3,
      "keyword": "빛과전자",
      "traffic": "200+"
    },
    {
      "rank": 4,
      "keyword": "가격",
      "traffic": "200+"
    },
    {
      "rank": 5,
      "keyword": "민희진",
      "traffic": "500+"
    },
    {
      "rank": 6,
      "keyword": "축제",
      "traffic": "500+"
    },
    {
      "rank": 7,
      "keyword": "달",
      "traffic": "200+"
    },
    {
      "rank": 8,
      "keyword": "콩고 민주 공화국",
      "traffic": "200+"
    },
    {
      "rank": 9,
      "keyword": "한능검 78회",
      "traffic": "1000+"
    },
    {
      "rank": 10,
      "keyword": "로켓",
      "traffic": "500+"
    }
  ],
  "domestic": [
    {
      "rank": 1,
      "keyword": "이수빈 결혼 발표",
      "state": "+",
      "change": "2"
    },
    {
      "rank": 2,
      "keyword": "김종훈 김두겸 지지 호소",
      "state": "-",
      "change": "1"
    },
    {
      "rank": 3,
      "keyword": "김하성 연장 승리 기여",
      "state": "+",
      "change": "9"
    },
    {
      "rank": 4,
      "keyword": "거리 유세하는 후보들",
      "state": "s",
      "change": "0"
    },
    {
      "rank": 5,
      "keyword": "염경엽 감독의 다양한 모습",
      "state": "-",
      "change": "3"
    },
    {
      "rank": 6,
      "keyword": "버스전용차로 위반 사과",
      "state": "n",
      "change": "0"
    },
    {
      "rank": 7,
      "keyword": "오세훈 재개발 기초도 몰라",
      "state": "n",
      "change": "0"
    },
    {
      "rank": 8,
      "keyword": "반려묘 방치 많이 큰 딸",
      "state": "n",
      "change": "0"
    },
    {
      "rank": 9,
      "keyword": "해초 들불상 수상",
      "state": "n",
      "change": "0"
    },
    {
      "rank": 10,
      "keyword": "이스라엘 구금 활동가 성폭행 사건",
      "state": "n",
      "change": "0"
    }
  ]
}