{
  "updatedAt": "2026-05-18T09:43:56.305Z",
  "google": [
    {
      "rank": 1,
      "keyword": "철도",
      "traffic": "2000+"
    },
    {
      "rank": 2,
      "keyword": "진",
      "traffic": "100+"
    },
    {
      "rank": 3,
      "keyword": "교도관",
      "traffic": "500+"
    },
    {
      "rank": 4,
      "keyword": "국립산림과학원",
      "traffic": "200+"
    },
    {
      "rank": 5,
      "keyword": "국제선",
      "traffic": "200+"
    },
    {
      "rank": 6,
      "keyword": "황연주",
      "traffic": "1000+"
    },
    {
      "rank": 7,
      "keyword": "예금",
      "traffic": "10000+"
    },
    {
      "rank": 8,
      "keyword": "한지민",
      "traffic": "200+"
    },
    {
      "rank": 9,
      "keyword": "진성",
      "traffic": "5000+"
    },
    {
      "rank": 10,
      "keyword": "앙투안 그리즈만",
      "traffic": "1000+"
    }
  ],
  "domestic": [
    {
      "rank": 1,
      "keyword": "와일드 씽 강동원과 코미디 도전",
      "state": "+",
      "change": "1"
    },
    {
      "rank": 2,
      "keyword": "출국하는 홍명보 감독",
      "state": "n",
      "change": "0"
    },
    {
      "rank": 3,
      "keyword": "롯데, 어피니티와 매각 중단",
      "state": "n",
      "change": "0"
    },
    {
      "rank": 4,
      "keyword": "빅뱅 태양 20주년 앨범 컴백",
      "state": "+",
      "change": "2"
    },
    {
      "rank": 5,
      "keyword": "GTX 철근 누락 논란",
      "state": "-",
      "change": "1"
    },
    {
      "rank": 6,
      "keyword": "탱크데이 스타벅스 이벤트에",
      "state": "n",
      "change": "0"
    },
    {
      "rank": 7,
      "keyword": "삼성전자 노사 평행선 지속",
      "state": "n",
      "change": "0"
    },
    {
      "rank": 8,
      "keyword": "이재명, 남광주 방문",
      "state": "n",
      "change": "0"
    },
    {
      "rank": 9,
      "keyword": "가천대 길병원 중증응급병원",
      "state": "n",
      "change": "0"
    },
    {
      "rank": 10,
      "keyword": "정혜성, 나솔사계 MC 합류",
      "state": "n",
      "change": "0"
    }
  ]
}